cb_bsdl_parser/CBBsdl.g4
cb_bsdl_parser/CBBsdl.interp
cb_bsdl_parser/CBBsdl.tokens
cb_bsdl_parser/CBBsdlLexer.g4
cb_bsdl_parser/CBBsdlLexer.interp
cb_bsdl_parser/CBBsdlLexer.py
cb_bsdl_parser/CBBsdlLexer.tokens
cb_bsdl_parser/CBBsdlListener.py
cb_bsdl_parser/CBBsdlParser.py
cb_bsdl_parser/Makefile
cb_bsdl_parser/__init__.py
cb_bsdl_parser/cb_bsdl.py
cb_bsdl_parser/.antlr/CBBsdl.interp
cb_bsdl_parser/.antlr/CBBsdl.tokens
cb_bsdl_parser/.antlr/CBBsdlLexer.interp
cb_bsdl_parser/.antlr/CBBsdlLexer.java
cb_bsdl_parser/.antlr/CBBsdlLexer.tokens
cb_bsdl_parser/.antlr/CBBsdlParser.java
cb_bsdl_tools/__init__.py
cb_bsdl_tools/cb_bsdl_check.py
cb_bsdl_tools/cb_bsdl_info.py
cb_bsdl_parser-0.7.2.dist-info/METADATA
cb_bsdl_parser-0.7.2.dist-info/WHEEL
cb_bsdl_parser-0.7.2.dist-info/entry_points.txt
cb_bsdl_parser-0.7.2.dist-info/licenses/LICENSE
cb_bsdl_parser-0.7.2.dist-info/RECORD
