Metadata-Version: 2.4
Name: cb_bsdl_parser
Version: 0.7.2
Summary: Chriesibaum's BSDL file parser
Project-URL: Homepage, https://github.com/chriesibaum/cb_bsdl_parser
Project-URL: Documentation, https://chriesibaum.github.io/cb_bsdl_parser/
Project-URL: Repository, https://github.com/chriesibaum/cb_bsdl_parser
Author-email: Thomas <Thomas@chriesibaum.dev>
License:                                  Apache License
License-File: LICENSE
Classifier: License :: OSI Approved :: Apache Software License
Classifier: Operating System :: OS Independent
Classifier: Programming Language :: Python :: 3.12
Requires-Python: >=3.12
Requires-Dist: antlr4-python3-runtime
Requires-Dist: cb-pyutils
